MineCrafter.py
minecrafter_fromkletochkarucka_1209-0.0.2.dist-info/licenses/LICENSE.txt
minecrafter_fromkletochkarucka_1209-0.0.2.dist-info/METADATA
minecrafter_fromkletochkarucka_1209-0.0.2.dist-info/WHEEL
minecrafter_fromkletochkarucka_1209-0.0.2.dist-info/top_level.txt
minecrafter_fromkletochkarucka_1209-0.0.2.dist-info/RECORD
