Metadata-Version: 2.4
Name: MineCrafter_FromKletochkarucka_1209
Version: 0.0.2
Summary: A cool crafter for Minecraft!
Author-email: Kletochkarucka <Kletochkarucka@gmail.com>
License: MIT License
Classifier: Programming Language :: Python :: 3
Classifier: Operating System :: OS Independent
Requires-Python: >=3.9
License-File: LICENSE.txt
Requires-Dist: requests>=2.32.3
Requires-Dist: beautifulsoup4>=4.12.3
Requires-Dist: pandas>=2.2.3
Dynamic: license-file
